TilesetParser/__init__.py
TilesetParser/main.py
TilesetParser/src/__init__.py
TilesetParser/src/find_tile.py
TilesetParser/src/gui.py
TilesetParser-1.0.5.2.dist-info/LICENSE
TilesetParser-1.0.5.2.dist-info/METADATA
TilesetParser-1.0.5.2.dist-info/WHEEL
TilesetParser-1.0.5.2.dist-info/entry_points.txt
TilesetParser-1.0.5.2.dist-info/top_level.txt
TilesetParser-1.0.5.2.dist-info/RECORD
